specops_cli/__init__.py
specops_cli-0.1.2.dist-info/METADATA
specops_cli-0.1.2.dist-info/WHEEL
specops_cli-0.1.2.dist-info/entry_points.txt
specops_cli-0.1.2.dist-info/RECORD
