Metadata-Version: 2.4
Name: specops-cli
Version: 0.1.2
Summary: SpecOps CLI, part of DotLabs Spec Ops. A tool to bootstrap your projects for Spec-Driven Infrastructure as Code.
Requires-Python: >=3.11
Requires-Dist: httpx[socks]
Requires-Dist: platformdirs
Requires-Dist: readchar
Requires-Dist: rich
Requires-Dist: truststore>=0.10.4
Requires-Dist: typer
